<?xml version="1.0" encoding="UTF-8" standalone="no"?>
<com.exactpro.test.SomeBean>
    <someString>string</someString>
    <someInt>50</someInt>
    <someFloat>0.0</someFloat>
    <aBoolean>false</aBoolean>
    <someInteger>3222</someInteger>
    <someDecimal>42</someDecimal>
    <someList>
        <com.exactpro.test.SomeBean>
            <someString>string</someString>
            <someInt>60</someInt>
            <someFloat>0.0</someFloat>
            <aBoolean>false</aBoolean>
            <someInteger>null</someInteger>
            <someDecimal>42</someDecimal>
            <someList>null</someList>
            <someMap>null</someMap>
            <someSet>null</someSet>
            <someBean>
                <com.exactpro.test.SomeBean>
                    <someString>null</someString>
                    <someInt>0</someInt>
                    <someFloat>0.0</someFloat>
                    <aBoolean>false</aBoolean>
                    <someInteger>null</someInteger>
                    <someDecimal>null</someDecimal>
                    <someList>null</someList>
                    <someMap>null</someMap>
                    <someSet>null</someSet>
                    <someBean>null</someBean>
                    <instant>null</instant>
                </com.exactpro.test.SomeBean>
            </someBean>
            <instant>null</instant>
        </com.exactpro.test.SomeBean>
    </someList>
    <someMap>
        <Entry>
            <com.exactpro.test.SomeBean>
                <someString>null</someString>
                <someInt>0</someInt>
                <someFloat>0.0</someFloat>
                <aBoolean>false</aBoolean>
                <someInteger>null</someInteger>
                <someDecimal>null</someDecimal>
                <someList>null</someList>
                <someMap>null</someMap>
                <someSet>null</someSet>
                <someBean>null</someBean>
                <instant>null</instant>
            </com.exactpro.test.SomeBean>
            <com.exactpro.test.SomeBean>
                <someString>null</someString>
                <someInt>0</someInt>
                <someFloat>0.0</someFloat>
                <aBoolean>false</aBoolean>
                <someInteger>null</someInteger>
                <someDecimal>null</someDecimal>
                <someList>null</someList>
                <someMap>null</someMap>
                <someSet>null</someSet>
                <someBean>null</someBean>
                <instant>null</instant>
            </com.exactpro.test.SomeBean>
        </Entry>
        <Entry>
            <com.exactpro.test.SomeBean>
                <someString>null</someString>
                <someInt>0</someInt>
                <someFloat>0.0</someFloat>
                <aBoolean>false</aBoolean>
                <someInteger>null</someInteger>
                <someDecimal>null</someDecimal>
                <someList>null</someList>
                <someMap>null</someMap>
                <someSet>null</someSet>
                <someBean>null</someBean>
                <instant>null</instant>
            </com.exactpro.test.SomeBean>
            <com.exactpro.test.SomeBean>
                <someString>null</someString>
                <someInt>0</someInt>
                <someFloat>0.0</someFloat>
                <aBoolean>false</aBoolean>
                <someInteger>null</someInteger>
                <someDecimal>null</someDecimal>
                <someList>null</someList>
                <someMap>null</someMap>
                <someSet>null</someSet>
                <someBean>null</someBean>
                <instant>null</instant>
            </com.exactpro.test.SomeBean>
        </Entry>
    </someMap>
    <someSet>
        <java.lang.Integer>6</java.lang.Integer>
    </someSet>
    <someBean>
        <com.exactpro.test.SomeBean>
            <someString>string</someString>
            <someInt>60</someInt>
            <someFloat>0.0</someFloat>
            <aBoolean>false</aBoolean>
            <someInteger>null</someInteger>
            <someDecimal>42</someDecimal>
            <someList>null</someList>
            <someMap>null</someMap>
            <someSet>null</someSet>
            <someBean>
                <com.exactpro.test.SomeBean>
                    <someString>null</someString>
                    <someInt>0</someInt>
                    <someFloat>0.0</someFloat>
                    <aBoolean>false</aBoolean>
                    <someInteger>null</someInteger>
                    <someDecimal>null</someDecimal>
                    <someList>null</someList>
                    <someMap>null</someMap>
                    <someSet>null</someSet>
                    <someBean>null</someBean>
                    <instant>null</instant>
                </com.exactpro.test.SomeBean>
            </someBean>
            <instant>null</instant>
        </com.exactpro.test.SomeBean>
    </someBean>
    <instant>2019-02-25T10:43:20.398944Z</instant>
</com.exactpro.test.SomeBean>
